Metadata-Version: 1.2
Name: fb2feed
Version: 0.2
Summary: Transforms Facebook pages to Atom feeds
Home-page: https://gitlab.com/philn/fb2feed
Author: Philippe Normand
Author-email: phil@base-art.net
License: MIT License
Keywords: facebook feed atom
Platform: UNKNOWN
Classifier: Environment :: Console
Classifier: Intended Audience :: End Users/Desktop
Classifier: Programming Language :: Python :: 3
Classifier: Topic :: Internet
Classifier: Topic :: Utilities
Classifier: License :: OSI Approved :: MIT License
Requires-Python: >=3.5
